{"Ads": [
    {
      "select_main_ads": "ADMOB",
      "select_backup_ads":"UNITY",
      "main_ads_banner": "ca-app-pub-8665352681989203/8186531104",
      "main_ads_intertitial":"",
      "backup_ads_banner":"4248527",
      "backup_ads_intertitial":"4248527",
      "interval_intertitial": 2,
      "initialize_sdk":"",
      "initialize_sdk_backup_ads":"",
      "high_paying_keyword_1": "Forex",
      "high_paying_keyword_2": "Insurance",
      "high_paying_keyword_3": "Binary Option",
      "high_paying_keyword_4": "Money",
      "high_paying_keyword_5": "Trading Forex",
      "status_app": "0",
      "link_redirect": "https://"
    }
  ]
}
